AUTHORS.rst
LICENSE
README.rst
setup.py
anduryl/__init__.py
anduryl/__main__.py
anduryl.egg-info/PKG-INFO
anduryl.egg-info/SOURCES.txt
anduryl.egg-info/dependency_links.txt
anduryl.egg-info/requires.txt
anduryl.egg-info/top_level.txt
anduryl/core/assessments.py
anduryl/core/calculate.py
anduryl/core/experts.py
anduryl/core/items.py
anduryl/core/main.py
anduryl/io/project.py
anduryl/io/reader.py
anduryl/io/savemodels.py
anduryl/io/settings.py
anduryl/io/table.py
anduryl/io/writer.py
anduryl/ui/__init__.py
anduryl/ui/assessments.py
anduryl/ui/dialogs.py
anduryl/ui/experts.py
anduryl/ui/items.py
anduryl/ui/main.py
anduryl/ui/menus.py
anduryl/ui/models.py
anduryl/ui/results.py
anduryl/ui/widgets.py
anduryl/core/assessments.py
anduryl/core/calculate.py
anduryl/core/experts.py
anduryl/core/items.py
anduryl/core/main.py
anduryl/data/icon.gif
anduryl/data/icon.ico
anduryl/data/splash_loading.png
anduryl/io/project.py
anduryl/io/reader.py
anduryl/io/savemodels.py
anduryl/io/settings.py
anduryl/io/table.py
anduryl/io/writer.py
anduryl/ui/__init__.py
anduryl/ui/assessments.py
anduryl/ui/dialogs.py
anduryl/ui/experts.py
anduryl/ui/items.py
anduryl/ui/main.py
anduryl/ui/menus.py
anduryl/ui/models.py
anduryl/ui/results.py
anduryl/ui/widgets.py